earthkit/climate/__init__.py
earthkit/climate/version.py
earthkit/climate/api/__init__.py
earthkit/climate/api/wrapper.py
earthkit/climate/indicators/__init__.py
earthkit/climate/indicators/precipitation.py
earthkit/climate/indicators/temperature.py
earthkit/climate/utils/__init__.py
earthkit/climate/utils/conversions.py
earthkit/climate/utils/percentile.py
earthkit/climate/utils/provenance.py
earthkit/climate/utils/units.py
earthkit_climate-0.2.0.dist-info/licenses/LICENSE
earthkit_climate-0.2.0.dist-info/METADATA
earthkit_climate-0.2.0.dist-info/WHEEL
earthkit_climate-0.2.0.dist-info/top_level.txt
earthkit_climate-0.2.0.dist-info/RECORD
